djangorestframework_features-0.1.2.dist-info/METADATA
djangorestframework_features-0.1.2.dist-info/RECORD
djangorestframework_features-0.1.2.dist-info/DESCRIPTION.rst
djangorestframework_features-0.1.2.dist-info/metadata.json
djangorestframework_features-0.1.2.dist-info/WHEEL
djangorestframework_features-0.1.2.dist-info/top_level.txt
rest_framework_features/schema.py
rest_framework_features/urls.py
rest_framework_features/__init__.py
rest_framework_features/test.py
rest_framework_features/apps.py
rest_framework_features/models.py
rest_framework_features/settings.py
rest_framework_features/permissions.py
rest_framework_features/__pycache__/models.cpython-37.pyc
rest_framework_features/__pycache__/settings.cpython-37.pyc
rest_framework_features/__pycache__/__init__.cpython-37.pyc
rest_framework_features/__pycache__/schema.cpython-37.pyc
rest_framework_features/__pycache__/test.cpython-37.pyc
rest_framework_features/__pycache__/permissions.cpython-37.pyc
rest_framework_features/__pycache__/apps.cpython-37.pyc
rest_framework_features/__pycache__/urls.cpython-37.pyc
rest_framework_features/management/__init__.py
rest_framework_features/management/__pycache__/__init__.cpython-37.pyc
rest_framework_features/management/commands/__init__.py
rest_framework_features/management/commands/features.py
rest_framework_features/management/commands/__pycache__/__init__.cpython-37.pyc
rest_framework_features/management/commands/__pycache__/features.cpython-37.pyc
rest_framework_features/templates/rest_framework_features/feature_locale.js
rest_framework_features/templates/rest_framework_features/feature_schema.json
rest_framework_features/templates/rest_framework_features/feature_locale.py
