Metadata-Version: 2.0
Name: djangorestframework-features
Version: 0.1.2
Summary: Advanced schema generation based on named features
Home-page: https://github.com/cloudcode-hungary/django-rest-framework-features
Author: Balina Bálint
Author-email: balintb@cloudcode.hu
License: BSD
Platform: UNKNOWN
Classifier: Development Status :: 2 - Pre-Alpha
Classifier: Environment :: Web Environment
Classifier: Framework :: Django
Classifier: Intended Audience :: Developers
Classifier: License :: OSI Approved :: BSD License
Classifier: Operating System :: OS Independent
Classifier: Natural Language :: English
Classifier: Programming Language :: Python :: 3.6
Classifier: Topic :: Internet :: WWW/HTTP
